Atv Pratica 4/full_adder/full_adder.v
module full_adder(a, b, cIn, s, cOut);

    input a, b, cIn;
    output s, cOut;

    assign s = a ^ b ^ cIn;
    assign cOut = (b & cIn) | (a & cIn) | (a & b);

endmodule

Atv Pratica 4/full_adder/full_adder_tb.v
`timescale 1ns/1ns
`include "full_adder.v"

module full_adder_tb;

    reg a, b, cIn;
    wire s, cOut;
    full_adder uut(a, b, cIn, s, cOut);

    initial begin
        $dumpfile("full_adder_tb.vcd");
        $dumpvars(0, full_adder_tb);

        a = 0; b = 0; cIn = 0; #10;
        a = 0; b = 0; cIn = 1; #10;
        a = 0; b = 1; cIn = 0; #10;
        a = 0; b = 1; cIn = 1; #10;
        a = 1; b = 0; cIn = 0; #10;
        a = 1; b = 0; cIn = 1; #10;
        a = 1; b = 1; cIn = 0; #10;
        a = 1; b = 1; cIn = 1; #10;

        $display("Teste completo");
    end

endmodule

Atv Pratica 4/full_adder/full_adder_tb.vcd
$date
	Fri Sep 27 09:03:56 2024
$end
$version
	Icarus Verilog
$end
$timescale
	1ns
$end
$scope module full_adder_tb $end
$var wire 1 ! s $end
$var wire 1 " cOut $end
$var reg 1 # a $end
$var reg 1 $ b $end
$var reg 1 % cIn $end
$scope module uut $end
$var wire 1 # a $end
$var wire 1 $ b $end
$var wire 1 % cIn $end
$var wire 1 " cOut $end
$var wire 1 ! s $end
$upscope $end
$upscope $end
$enddefinitions $end
$comment Show the parameter values. $end
$dumpall
$end
#0
$dumpvars
0%
0$
0#
0"
0!
$end
#10
1!
1%
#20
0%
1$
#30
1"
0!
1%
#40
0"
1!
0%
0$
1#
#50
1"
0!
1%
#60
0%
1$
#70
1!
1%
