Atv Pratica 6/contador-sincrono/contador.v
module contador(pr, clr, clk, q);

    input pr, clr, clk;
    output reg [3:0] q;

    always @(posedge clk) begin
        if (pr == 0 & clr == 1)
            q = 1;
        else if (pr == 1 & clr == 0)
            q = 0;
        else if (pr == 1 & clr == 1)
            q <= q + 1'b1;
    end

endmodule

Atv Pratica 6/contador-assincrono/contador_tb.v
`timescale 1ns/1ns
`include "contador.v"

module contador_tb;

    reg pr, clr, clk;
    wire [3:0] q;
    contador uut(pr, clr, clk, q);

    initial begin
        $dumpfile ("contador.vcd");
        $dumpvars (1);

        pr = 1; clr = 0; #20;
        pr = 1; clr = 1; #340;

        $finish;
    end

    initial begin
        clk = 0;
        forever #10 clk = ~ clk ;
    end


endmodule

Atv Pratica 6/contador-sincrono/contador.vcd
$date
	Fri Oct 25 10:18:15 2024
$end
$version
	Icarus Verilog
$end
$timescale
	1ns
$end
$scope module contador_tb $end
$var wire 4 ! q [3:0] $end
$var reg 1 " clk $end
$var reg 1 # clr $end
$var reg 1 $ pr $end
$upscope $end
$enddefinitions $end
$comment Show the parameter values. $end
$dumpall
$end
#0
$dumpvars
1$
0#
0"
bx !
$end
#10
b0 !
1"
#20
0"
1#
#30
b1 !
1"
#40
0"
#50
b10 !
1"
#60
0"
#70
b11 !
1"
#80
0"
#90
b100 !
1"
#100
0"
#110
b101 !
1"
#120
0"
#130
b110 !
1"
#140
0"
#150
b111 !
1"
#160
0"
#170
b1000 !
1"
#180
0"
#190
b1001 !
1"
#200
0"
#210
b1010 !
1"
#220
0"
#230
b1011 !
1"
#240
0"
#250
b1100 !
1"
#260
0"
#270
b1101 !
1"
#280
0"
#290
b1110 !
1"
#300
0"
#310
b1111 !
1"
#320
0"
#330
b0 !
1"
#340
0"
#350
b1 !
1"
