Atv Pratica 3/bcd/bcd.v
module bcd_gate(a, y);

    input [3:0] a;
    output reg [6:0] y;

    always @(a) begin
        case (a)
            4'b0000: y = 7'b1111110; //0
            4'b0001: y = 7'b0110000; //1
            4'b0010: y = 7'b1101101; //2
            4'b0011: y = 7'b1111001; //3
            4'b0100: y = 7'b0110011; //4
            4'b0101: y = 7'b1011011; //5
            4'b0110: y = 7'b1011111; //6
            4'b0111: y = 7'b1110000; //7
            4'b1000: y = 7'b1111111; //8
            4'b1001: y = 7'b1111011; //9
            4'b1010: y = 7'b1110111; //A
            4'b1011: y = 7'b0011111; //B
            4'b1100: y = 7'b1001110; //C
            4'b1101: y = 7'b0111101; //D
            4'b1110: y = 7'b1001111; //E
            4'b1111: y = 7'b1000111; //F
            default: y = 7'b0000000;
        endcase
    end

endmodule

Atv Pratica 3/bcd/bcd_tb.v
`timescale 1ns/1ns
`include "bcd.v"

module bcd_tb;

    reg [3:0] a;
    wire [6:0] y;
    bcd_gate uut(a, y);

    initial begin
        $dumpfile("bcd_tb.vcd");
        $dumpvars(0, bcd_tb);

        a = 4'b0000; #10;
        a = 4'b0001; #10;
        a = 4'b0010; #10;
        a = 4'b0011; #10;
        a = 4'b0100; #10;
        a = 4'b0101; #10;
        a = 4'b0110; #10;
        a = 4'b0111; #10;
        a = 4'b1000; #10;
        a = 4'b1001; #10;
        a = 4'b1010; #10;
        a = 4'b1011; #10;
        a = 4'b1100; #10;
        a = 4'b1101; #10;
        a = 4'b1110; #10;
        a = 4'b1111; #10;

        $display("Teste completo");
    end

endmodule

Atv Pratica 3/bcd/bcd_tb.vcd
$date
	Fri Sep 20 08:38:56 2024
$end
$version
	Icarus Verilog
$end
$timescale
	1ns
$end
$scope module bcd_tb $end
$var wire 7 ! y [6:0] $end
$var reg 4 " a [3:0] $end
$scope module uut $end
$var wire 4 # a [3:0] $end
$var reg 7 $ y [6:0] $end
$upscope $end
$upscope $end
$enddefinitions $end
$comment Show the parameter values. $end
$dumpall
$end
#0
$dumpvars
b1111110 $
b0 #
b0 "
b1111110 !
$end
#10
b110000 !
b110000 $
b1 "
b1 #
#20
b1101101 !
b1101101 $
b10 "
b10 #
#30
b1111001 !
b1111001 $
b11 "
b11 #
#40
b110011 !
b110011 $
b100 "
b100 #
#50
b1011011 !
b1011011 $
b101 "
b101 #
#60
b1011111 !
b1011111 $
b110 "
b110 #
#70
b1110000 !
b1110000 $
b111 "
b111 #
#80
b1111111 !
b1111111 $
b1000 "
b1000 #
#90
b1111011 !
b1111011 $
b1001 "
b1001 #
#100
b1110111 !
b1110111 $
b1010 "
b1010 #
#110
b11111 !
b11111 $
b1011 "
b1011 #
#120
b1001110 !
b1001110 $
b1100 "
b1100 #
#130
b111101 !
b111101 $
b1101 "
b1101 #
#140
b1001111 !
b1001111 $
b1110 "
b1110 #
#150
b1000111 !
b1000111 $
b1111 "
b1111 #
